{
    "history": [
        {
            "bsn": "60076",
            "snA": "6291500",
            "floor": [
                1,
                999999
            ],
            "date": "2021-04-26"
        },
        {
            "bsn": "60076",
            "snA": "6291500",
            "floor": [
                1,
                999999
            ],
            "date": "2021-04-26"
        },
        {
            "bsn": "60076",
            "snA": "6291500",
            "floor": [
                1,
                12
            ],
            "date": "2021-04-26"
        }
    ]
}